nlweb_network/__init__.py
nlweb_network/server.py
nlweb_network/interfaces/__init__.py
nlweb_network/interfaces/a2a_sse.py
nlweb_network/interfaces/a2a_streamable.py
nlweb_network/interfaces/base.py
nlweb_network/interfaces/http_json.py
nlweb_network/interfaces/http_sse.py
nlweb_network/interfaces/mcp_sse.py
nlweb_network/interfaces/mcp_streamable.py
nlweb_network/static/index.html
nlweb_network/static/nlweb-chat.css
nlweb_network/static/nlweb-chat.js
nlweb_network-0.5.42.dist-info/METADATA
nlweb_network-0.5.42.dist-info/WHEEL
nlweb_network-0.5.42.dist-info/entry_points.txt
nlweb_network-0.5.42.dist-info/top_level.txt
nlweb_network-0.5.42.dist-info/RECORD
