Metadata-Version: 2.4
Name: nlweb-network
Version: 0.5.42
Summary: Network interfaces and server for NLWeb - HTTP, MCP, and A2A protocol adapters
Author: Microsoft Corporation
License: MIT
Project-URL: Homepage, https://github.com/nlweb-ai/NLWeb_Core
Project-URL: Repository, https://github.com/nlweb-ai/NLWeb_Core
Classifier: Development Status :: 4 - Beta
Classifier: Intended Audience :: Developers
Classifier: License :: OSI Approved :: MIT License
Classifier: Programming Language :: Python :: 3
Classifier: Programming Language :: Python :: 3.9
Classifier: Programming Language :: Python :: 3.10
Classifier: Programming Language :: Python :: 3.11
Classifier: Programming Language :: Python :: 3.12
Requires-Python: >=3.9
Requires-Dist: nlweb-core>=0.5.42
Requires-Dist: aiohttp>=3.8.0
Requires-Dist: aiohttp-cors>=0.7.0
Provides-Extra: dev
Requires-Dist: pytest>=7.0.0; extra == "dev"
Requires-Dist: pytest-asyncio>=0.21.0; extra == "dev"
